kopylot/__init__.py
kopylot/audit.py
kopylot/chat.py
kopylot/cli.py
kopylot/diagnose.py
kopylot/llm.py
kopylot/prompts.py
kopylot/utils.py
kopylot/version.py
kopylot-0.0.4.dist-info/LICENSE
kopylot-0.0.4.dist-info/METADATA
kopylot-0.0.4.dist-info/WHEEL
kopylot-0.0.4.dist-info/entry_points.txt
kopylot-0.0.4.dist-info/RECORD
