Metadata-Version: 2.1
Name: kopylot
Version: 0.0.4
Summary: Your AI Powered Kubernetes Assistant
Home-page: https://github.com/avsthiago/kopylot
Author: Thiago Alves
Requires-Python: >=3.8,<4.0
Classifier: Programming Language :: Python :: 3
Classifier: Programming Language :: Python :: 3.8
Classifier: Programming Language :: Python :: 3.9
Classifier: Programming Language :: Python :: 3.10
Classifier: Programming Language :: Python :: 3.11
Requires-Dist: inquirerpy (>=0.3.4,<0.4.0)
Requires-Dist: openai (>=0.27.2,<0.28.0)
Requires-Dist: rich (>=13.3.3,<14.0.0)
Requires-Dist: typer (>=0.7.0,<0.8.0)
Project-URL: Documentation, https://avsthiago.github.io/kopylot/
Project-URL: Repository, https://github.com/avsthiago/kopylot
